fortiedr/__init__.py
fortiedr/api_parameters.json
fortiedr/auth.py
fortiedr/connector.py
fortiedr/fortiedr.py
fortiedr-3.9.2.dist-info/licenses/LICENSE
fortiedr-3.9.2.dist-info/METADATA
fortiedr-3.9.2.dist-info/WHEEL
fortiedr-3.9.2.dist-info/top_level.txt
fortiedr-3.9.2.dist-info/RECORD
